ds_connector/__init__.py
ds_connector/api/__init__.py
ds_connector/api/data_product_api.py
ds_connector/api/default_api.py
ds_connector/api/items_api.py
ds_connector/api_client.py
ds_connector/api_response.py
ds_connector/configuration.py
ds_connector/exceptions.py
ds_connector/models/__init__.py
ds_connector/models/connector.py
ds_connector/models/data_product.py
ds_connector/models/example_response.py
ds_connector/models/health_check.py
ds_connector/models/http_validation_error.py
ds_connector/models/interface.py
ds_connector/models/item.py
ds_connector/models/paginated_result.py
ds_connector/models/source.py
ds_connector/models/tag.py
ds_connector/models/validation_error.py
ds_connector/models/validation_error_loc_inner.py
ds_connector/py.typed
ds_connector/rest.py
ds_connector-0.1.1.dist-info/LICENSE
ds_connector-0.1.1.dist-info/METADATA
ds_connector-0.1.1.dist-info/WHEEL
ds_connector-0.1.1.dist-info/RECORD
